rescalex/__init__.py
rescalex/rescale.py
rescalex-1.0.1.dist-info/LICENSE
rescalex-1.0.1.dist-info/METADATA
rescalex-1.0.1.dist-info/WHEEL
rescalex-1.0.1.dist-info/top_level.txt
rescalex-1.0.1.dist-info/RECORD
