Metadata-Version: 2.1
Name: rescalex
Version: 1.0.1
Summary: UNKNOWN
Home-page: https://github.com/bkornpob/rescale
Author: Kornpob Bhirombhakdi
Author-email: kbhirombhakdi@stsci.edu
License: UNKNOWN
Platform: UNKNOWN
Classifier: Programming Language :: Python :: 3
Classifier: License :: OSI Approved :: MIT License
Classifier: Operating System :: OS Independent
Requires-Python: >=3
